Metadata-Version: 2.4
Name: mcp-server-weather-cjshen
Version: 0.1.0
Summary: 实现类weather功能的MCP⼯具
Requires-Python: >=3.12
Requires-Dist: dotenv>=0.9.9
Requires-Dist: mcp>=1.14.0
Requires-Dist: numpy>=2.3.3
Requires-Dist: openai>=1.107.3
Requires-Dist: openapi>=2.0.0
Requires-Dist: pandas>=2.3.3
Requires-Dist: pymysql>=1.1.2
Requires-Dist: python-dotenv>=1.1.1
